rust_ephem/__init__.py
rust_ephem/__init__.pyi
rust_ephem/_rust_ephem.cpython-312-aarch64-linux-gnu.so
rust_ephem/_rust_ephem.pyi
rust_ephem/constraints.py
rust_ephem/constraints.pyi
rust_ephem/ephemeris.py
rust_ephem/ephemeris.pyi
rust_ephem/py.typed
rust_ephem/tle.py
rust_ephem/tle.pyi
rust_ephem-0.3.1.dist-info/METADATA
rust_ephem-0.3.1.dist-info/WHEEL
rust_ephem-0.3.1.dist-info/licenses/LICENSE
rust_ephem-0.3.1.dist-info/RECORD
