Metadata-Version: 2.4
Name: rust-ephem
Version: 0.3.1
Classifier: Development Status :: 3 - Alpha
Classifier: Intended Audience :: Science/Research
Classifier: Intended Audience :: Developers
Classifier: License :: OSI Approved :: Apache Software License
Classifier: Operating System :: OS Independent
Classifier: Operating System :: POSIX :: Linux
Classifier: Operating System :: MacOS
Classifier: Operating System :: Microsoft :: Windows
Classifier: Programming Language :: Python :: 3
Classifier: Programming Language :: Python :: 3.10
Classifier: Programming Language :: Python :: 3.11
Classifier: Programming Language :: Python :: 3.12
Classifier: Programming Language :: Python :: 3.13
Classifier: Programming Language :: Python :: 3 :: Only
Classifier: Programming Language :: Python :: Implementation :: CPython
Classifier: Programming Language :: Rust
Classifier: Typing :: Typed
Classifier: Topic :: Scientific/Engineering :: Astronomy
Classifier: Topic :: Scientific/Engineering :: Physics
Classifier: Topic :: Software Development :: Libraries :: Python Modules
Requires-Dist: numpy>=1.16
Requires-Dist: pydantic>=2.12.4
Requires-Dist: pytest>=7.0 ; extra == 'all'
Requires-Dist: astropy>=5.0 ; extra == 'all'
Requires-Dist: pluggy>=1.6.0 ; extra == 'all'
Requires-Dist: sphinx>=6.0 ; extra == 'all'
Requires-Dist: sphinx-rtd-theme ; extra == 'all'
Requires-Dist: mypy ; extra == 'dev'
Requires-Dist: ruff ; extra == 'dev'
Requires-Dist: prek ; extra == 'dev'
Requires-Dist: sphinx>=6.0 ; extra == 'docs'
Requires-Dist: sphinx-rtd-theme ; extra == 'docs'
Requires-Dist: maturin>=1.0 ; extra == 'docs'
Requires-Dist: pytest>=7.0 ; extra == 'test'
Requires-Dist: astropy>=5.0 ; extra == 'test'
Requires-Dist: pluggy>=1.6.0 ; extra == 'test'
Requires-Dist: pytest-cov>=7.0.0 ; extra == 'test'
Provides-Extra: all
Provides-Extra: dev
Provides-Extra: docs
Provides-Extra: test
License-File: LICENSE
Summary: High-performance satellite ephemeris and visibility calculations with Rust and astropy integration
Keywords: satellite,ephemeris,sgp4,tle,spice,orbital-mechanics,astronomy,astropy,visibility,constraints
Author-email: "Jamie A. Kennea" <jamie@cosmicfrontier.org>
Maintainer-email: "Jamie A. Kennea" <jamie@cosmicfrontier.org>
License: Apache-2.0
Requires-Python: >=3.10
Project-URL: Bug Tracker, https://github.com/CosmicFrontierLabs/rust-ephem/issues
Project-URL: Changelog, https://github.com/CosmicFrontierLabs/rust-ephem/blob/main/CHANGELOG.md
Project-URL: Documentation, https://rust-ephem.readthedocs.io
Project-URL: Homepage, https://github.com/CosmicFrontierLabs/rust-ephem
Project-URL: Repository, https://github.com/CosmicFrontierLabs/rust-ephem
Project-URL: Source Code, https://github.com/CosmicFrontierLabs/rust-ephem
